{
  "hackathons": [
    {
      "id": 20750,
      "title": "Hack4Purpose",
      "displayed_location": {
        "icon": "map-marker-alt",
        "location": "Chennai"
      },
      "open_state": "open",
      "thumbnail_url": "https://d2dmyh35ffsxbl.cloudfront.net/assets/defaults/thumbnail-placeholder-8c916ef4da99a222ce6ece077c71c7e282f071f830747b2abb5718018cbfa699.gif",
      "analytics_identifier": "Hack4Purpose (20750)",
      "url": "https://hack4purpose.devpost.com/",
      "time_left_to_submission": "17 days left",
      "submission_period_dates": "Feb 26 - May 29, 2024",
      "themes": [
        {
          "id": 22,
          "name": "Open Ended"
        },
        {
          "id": 11,
          "name": "Productivity"
        },
        {
          "id": 13,
          "name": "Social Good"
        }
      ],
      "prize_amount": "₹ <span data-currency-value>100,000</span>",
      "registrations_count": 436,
      "featured": false,
      "organization_name": "DPurpose Foundation",
      "winners_announced": false,
      "submission_gallery_url": "https://hack4purpose.devpost.com/project-gallery",
      "start_a_submission_url": "https://hack4purpose.devpost.com/challenges/start_a_submission",
      "invite_only": false,
      "eligibility_requirement_invite_only_description": null,
      "managed_by_devpost_badge": false
    },
    {
      "id": 21144,
      "title": "CSCI 1470/2470 Deep Learning (Spring 2024)",
      "displayed_location": {
        "icon": "map-marker-alt",
        "location": "Providence, RI, USA"
      },
      "open_state": "open",
      "thumbnail_url": "//d112y698adiu2z.cloudfront.net/photos/production/challenge_thumbnails/002/834/540/datas/medium_square.png",
      "analytics_identifier": "CSCI 1470/2470 Deep Learning (Spring 2024) (21144)",
      "url": "https://deep-learning-spring-2024.devpost.com/",
      "time_left_to_submission": "about 4 hours left",
      "submission_period_dates": "Apr 05 - May 12, 2024",
      "themes": [
        {
          "id": 6,
          "name": "Machine Learning/AI"
        }
      ],
      "prize_amount": "$<span data-currency-value>30</span>",
      "registrations_count": 375,
      "featured": false,
      "organization_name": "Brown University",
      "winners_announced": false,
      "submission_gallery_url": "https://deep-learning-spring-2024.devpost.com/project-gallery",
      "start_a_submission_url": "https://deep-learning-spring-2024.devpost.com/challenges/start_a_submission",
      "invite_only": true,
      "eligibility_requirement_invite_only_description": "Brown CS Deep Learning (Spring 2024) students only",
      "managed_by_devpost_badge": false
    },
    {
      "id": 19519,
      "title": "Cheat Layer Hackathon II",
      "displayed_location": {
        "icon": "map-marker-alt",
        "location": "San Francisco"
      },
      "open_state": "open",
      "thumbnail_url": "//d112y698adiu2z.cloudfront.net/photos/production/challenge_thumbnails/002/648/662/datas/medium_square.png",
      "analytics_identifier": "Cheat Layer Hackathon II (19519)",
      "url": "https://cheat-layer.devpost.com/",
      "time_left_to_submission": "19 days left",
      "submission_period_dates": "Dec 15, 2023 - May 31, 2024",
      "themes": [
        {
          "id": 23,
          "name": "Beginner Friendly"
        },
        {
          "id": 17,
          "name": "Low/No Code"
        },
        {
          "id": 6,
          "name": "Machine Learning/AI"
        }
      ],
      "prize_amount": "$<span data-currency-value>1,050</span>",
      "registrations_count": 307,
      "featured": false,
      "organization_name": "Cheat Layer, inc.",
      "winners_announced": false,
      "submission_gallery_url": "https://cheat-layer.devpost.com/project-gallery",
      "start_a_submission_url": "https://cheat-layer.devpost.com/challenges/start_a_submission",
      "invite_only": false,
      "eligibility_requirement_invite_only_description": null,
      "managed_by_devpost_badge": false
    },
    {
      "id": 20671,
      "title": "Cipher Craft",
      "displayed_location": {
        "icon": "map-marker-alt",
        "location": "UET Lahore"
      },
      "open_state": "open",
      "thumbnail_url": "//d112y698adiu2z.cloudfront.net/photos/production/challenge_thumbnails/002/779/001/datas/medium_square.jpg",
      "analytics_identifier": "Cipher Craft (20671)",
      "url": "https://cipher-craft.devpost.com/",
      "time_left_to_submission": "27 days left",
      "submission_period_dates": "Feb 20 - Jun 08, 2024",
      "themes": [
        {
          "id": 23,
          "name": "Beginner Friendly"
        },
        {
          "id": 28,
          "name": "Databases"
        },
        {
          "id": 6,
          "name": "Machine Learning/AI"
        }
      ],
      "prize_amount": "$<span data-currency-value>0</span>",
      "registrations_count": 76,
      "featured": false,
      "organization_name": "MLH",
      "winners_announced": false,
      "submission_gallery_url": "https://cipher-craft.devpost.com/project-gallery",
      "start_a_submission_url": "https://cipher-craft.devpost.com/challenges/start_a_submission",
      "invite_only": false,
      "eligibility_requirement_invite_only_description": null,
      "managed_by_devpost_badge": false
    },
    {
      "id": 21341,
      "title": "Meta Llama 3 Hackathon",
      "displayed_location": {
        "icon": "map-marker-alt",
        "location": "Shack 15"
      },
      "open_state": "open",
      "thumbnail_url": "//d112y698adiu2z.cloudfront.net/photos/production/challenge_thumbnails/002/870/392/datas/medium_square.jpg",
      "analytics_identifier": "Meta Llama 3 Hackathon (21341)",
      "url": "https://metallama3.devpost.com/",
      "time_left_to_submission": "about 2 hours left",
      "submission_period_dates": "May 11 - 12, 2024",
      "themes": [
        {
          "id": 6,
          "name": "Machine Learning/AI"
        },
        {
          "id": 27,
          "name": "Robotic Process Automation"
        },
        {
          "id": 25,
          "name": "Web"
        }
      ],
      "prize_amount": "$<span data-currency-value>6,000</span>",
      "registrations_count": 64,
      "featured": false,
      "organization_name": "Cerebral Valley",
      "winners_announced": false,
      "submission_gallery_url": "https://metallama3.devpost.com/project-gallery",
      "start_a_submission_url": "https://metallama3.devpost.com/challenges/start_a_submission",
      "invite_only": false,
      "eligibility_requirement_invite_only_description": null,
      "managed_by_devpost_badge": false
    },
    {
      "id": 19950,
      "title": "2024 ESE4510 ESE Senior Design [Deliwala, van der Spiegel]",
      "displayed_location": {
        "icon": "map-marker-alt",
        "location": "Philadelphia, PA, USA"
      },
      "open_state": "open",
      "thumbnail_url": "https://d2dmyh35ffsxbl.cloudfront.net/assets/defaults/thumbnail-placeholder-8c916ef4da99a222ce6ece077c71c7e282f071f830747b2abb5718018cbfa699.gif",
      "analytics_identifier": "2024 ESE4510 ESE Senior Design [Deliwala, van der Spiegel] (19950)",
      "url": "https://ese4510s24.devpost.com/",
      "time_left_to_submission": "3 days left",
      "submission_period_dates": "Jan 02 - May 15, 2024",
      "themes": [
        {
          "id": 19,
          "name": "Education"
        }
      ],
      "prize_amount": "$<span data-currency-value>0</span>",
      "registrations_count": 64,
      "featured": false,
      "organization_name": "university of pennsylvania",
      "winners_announced": false,
      "submission_gallery_url": "https://ese4510s24.devpost.com/project-gallery",
      "start_a_submission_url": "https://ese4510s24.devpost.com/challenges/start_a_submission",
      "invite_only": true,
      "eligibility_requirement_invite_only_description": "university of Pennsylvania students only",
      "managed_by_devpost_badge": false
    },
    {
      "id": 19951,
      "title": "2024 ESE 1900 Silicon Garage",
      "displayed_location": {
        "icon": "map-marker-alt",
        "location": "Philadelphia, PA, USA"
      },
      "open_state": "open",
      "thumbnail_url": "https://d2dmyh35ffsxbl.cloudfront.net/assets/defaults/thumbnail-placeholder-8c916ef4da99a222ce6ece077c71c7e282f071f830747b2abb5718018cbfa699.gif",
      "analytics_identifier": "2024 ESE 1900 Silicon Garage (19951)",
      "url": "https://ese1900s24.devpost.com/",
      "time_left_to_submission": "3 days left",
      "submission_period_dates": "Feb 15 - May 15, 2024",
      "themes": [
        {
          "id": 19,
          "name": "Education"
        }
      ],
      "prize_amount": "$<span data-currency-value>0</span>",
      "registrations_count": 49,
      "featured": false,
      "organization_name": "university of pennsylvania",
      "winners_announced": false,
      "submission_gallery_url": "https://ese1900s24.devpost.com/project-gallery",
      "start_a_submission_url": "https://ese1900s24.devpost.com/challenges/start_a_submission",
      "invite_only": true,
      "eligibility_requirement_invite_only_description": "For those enrolled in ESE 1900",
      "managed_by_devpost_badge": false
    },
    {
      "id": 21377,
      "title": "Lisk BlockChange Africa 2024",
      "displayed_location": {
        "icon": "map-marker-alt",
        "location": "Zug, Switzerland"
      },
      "open_state": "open",
      "thumbnail_url": "//d112y698adiu2z.cloudfront.net/photos/production/challenge_thumbnails/002/879/215/datas/medium_square.jpeg",
      "analytics_identifier": "Lisk BlockChange Africa 2024 (21377)",
      "url": "https://lisk-blockchange-2024.devpost.com/",
      "time_left_to_submission": "19 days left",
      "submission_period_dates": "May 07 - 31, 2024",
      "themes": [
        {
          "id": 1,
          "name": "Blockchain"
        },
        {
          "id": 3,
          "name": "Fintech"
        },
        {
          "id": 4,
          "name": "Gaming"
        }
      ],
      "prize_amount": "$<span data-currency-value>2,000</span>",
      "registrations_count": 49,
      "featured": false,
      "organization_name": "aliu@dltafrica.io",
      "winners_announced": false,
      "submission_gallery_url": "https://lisk-blockchange-2024.devpost.com/project-gallery",
      "start_a_submission_url": "https://lisk-blockchange-2024.devpost.com/challenges/start_a_submission",
      "invite_only": false,
      "eligibility_requirement_invite_only_description": null,
      "managed_by_devpost_badge": false
    },
    {
      "id": 21261,
      "title": "IEEE Ottawa Robotics Competition (Arduino)",
      "displayed_location": {
        "icon": "map-marker-alt",
        "location": "All Saints High School"
      },
      "open_state": "open",
      "thumbnail_url": "//d112y698adiu2z.cloudfront.net/photos/production/challenge_thumbnails/002/872/819/datas/medium_square.png",
      "analytics_identifier": "IEEE Ottawa Robotics Competition (Arduino) (21261)",
      "url": "https://orcarduino.devpost.com/",
      "time_left_to_submission": "13 days left",
      "submission_period_dates": "May 01 - 25, 2024",
      "themes": [
        {
          "id": 23,
          "name": "Beginner Friendly"
        }
      ],
      "prize_amount": "$<span data-currency-value>0</span>",
      "registrations_count": 2,
      "featured": false,
      "organization_name": "IEEE Ottawa Robotics Competition",
      "winners_announced": false,
      "submission_gallery_url": "https://orcarduino.devpost.com/project-gallery",
      "start_a_submission_url": "https://orcarduino.devpost.com/challenges/start_a_submission",
      "invite_only": true,
      "eligibility_requirement_invite_only_description": "Registered and accepted teams",
      "managed_by_devpost_badge": false
    },
    {
      "id": 20752,
      "title": "DeveloperWeek AI/ML 2024 Hackathon sponsored by AWS",
      "displayed_location": {
        "icon": "map-marker-alt",
        "location": "Pier 27"
      },
      "open_state": "upcoming",
      "thumbnail_url": "//d112y698adiu2z.cloudfront.net/photos/production/challenge_thumbnails/002/886/009/datas/medium_square.jpg",
      "analytics_identifier": "DeveloperWeek AI/ML 2024 Hackathon sponsored by AWS (20752)",
      "url": "https://ai-devsummit-2024-hackathon.devpost.com/",
      "time_left_to_submission": "Upcoming",
      "submission_period_dates": "May 22, 2024",
      "themes": [
        {
          "id": 6,
          "name": "Machine Learning/AI"
        },
        {
          "id": 17,
          "name": "Low/No Code"
        },
        {
          "id": 2,
          "name": "DevOps"
        }
      ],
      "prize_amount": "$<span data-currency-value>33,200</span>",
      "registrations_count": 215,
      "featured": false,
      "organization_name": "DevNetwork",
      "winners_announced": false,
      "submission_gallery_url": "https://ai-devsummit-2024-hackathon.devpost.com/project-gallery",
      "start_a_submission_url": "https://ai-devsummit-2024-hackathon.devpost.com/challenges/start_a_submission",
      "invite_only": false,
      "eligibility_requirement_invite_only_description": null,
      "managed_by_devpost_badge": false
    },
    {
      "id": 21384,
      "title": "UCI Design-a-thon 2024: True to You",
      "displayed_location": {
        "icon": "map-marker-alt",
        "location": "University of California Irvine"
      },
      "open_state": "upcoming",
      "thumbnail_url": "//d112y698adiu2z.cloudfront.net/photos/production/challenge_thumbnails/002/888/087/datas/medium_square.png",
      "analytics_identifier": "UCI Design-a-thon 2024: True to You (21384)",
      "url": "https://uci-design-a-thon-2024.devpost.com/",
      "time_left_to_submission": "Upcoming",
      "submission_period_dates": "May 17 - 19, 2024",
      "themes": [
        {
          "id": 23,
          "name": "Beginner Friendly"
        },
        {
          "id": 18,
          "name": "Design"
        },
        {
          "id": 13,
          "name": "Social Good"
        }
      ],
      "prize_amount": "$<span data-currency-value>1,460</span>",
      "registrations_count": 142,
      "featured": false,
      "organization_name": "Design at UCI",
      "winners_announced": false,
      "submission_gallery_url": "https://uci-design-a-thon-2024.devpost.com/project-gallery",
      "start_a_submission_url": "https://uci-design-a-thon-2024.devpost.com/challenges/start_a_submission",
      "invite_only": false,
      "eligibility_requirement_invite_only_description": null,
      "managed_by_devpost_badge": false
    },
    {
      "id": 20764,
      "title": "BlockHack 2024 Spring",
      "displayed_location": {
        "icon": "map-marker-alt",
        "location": "George Brown College - Casa Loma Campus"
      },
      "open_state": "upcoming",
      "thumbnail_url": "//d112y698adiu2z.cloudfront.net/photos/production/challenge_thumbnails/002/873/057/datas/medium_square.png",
      "analytics_identifier": "BlockHack 2024 Spring (20764)",
      "url": "https://blockhack-2024-spring.devpost.com/",
      "time_left_to_submission": "Upcoming",
      "submission_period_dates": "May 24 - 26, 2024",
      "themes": [
        {
          "id": 23,
          "name": "Beginner Friendly"
        },
        {
          "id": 1,
          "name": "Blockchain"
        },
        {
          "id": 3,
          "name": "Fintech"
        }
      ],
      "prize_amount": "$CAD<span data-currency-value>6,000</span>",
      "registrations_count": 104,
      "featured": false,
      "organization_name": "Bitcoin Bay",
      "winners_announced": false,
      "submission_gallery_url": "https://blockhack-2024-spring.devpost.com/project-gallery",
      "start_a_submission_url": "https://blockhack-2024-spring.devpost.com/challenges/start_a_submission",
      "invite_only": false,
      "eligibility_requirement_invite_only_description": null,
      "managed_by_devpost_badge": false
    },
    {
      "id": 21101,
      "title": "MontyHacks VII",
      "displayed_location": {
        "icon": "map-marker-alt",
        "location": "Montgomery High School"
      },
      "open_state": "upcoming",
      "thumbnail_url": "//d112y698adiu2z.cloudfront.net/photos/production/challenge_thumbnails/002/831/574/datas/medium_square.png",
      "analytics_identifier": "MontyHacks VII (21101)",
      "url": "https://montyhacks-vii.devpost.com/",
      "time_left_to_submission": "Upcoming",
      "submission_period_dates": "May 18, 2024",
      "themes": [
        {
          "id": 23,
          "name": "Beginner Friendly"
        },
        {
          "id": 6,
          "name": "Machine Learning/AI"
        },
        {
          "id": 22,
          "name": "Open Ended"
        }
      ],
      "prize_amount": "$<span data-currency-value>39,002</span>",
      "registrations_count": 32,
      "featured": false,
      "organization_name": "Montgomery HS Computer Science Club",
      "winners_announced": false,
      "submission_gallery_url": "https://montyhacks-vii.devpost.com/project-gallery",
      "start_a_submission_url": "https://montyhacks-vii.devpost.com/challenges/start_a_submission",
      "invite_only": false,
      "eligibility_requirement_invite_only_description": null,
      "managed_by_devpost_badge": false
    },
    {
      "id": 18731,
      "title": "HackSimBuild 2024 - Registration is Open!",
      "displayed_location": {
        "icon": "map-marker-alt",
        "location": "Denver, Colorado, USA"
      },
      "open_state": "upcoming",
      "thumbnail_url": "https://d2dmyh35ffsxbl.cloudfront.net/assets/defaults/thumbnail-placeholder-8c916ef4da99a222ce6ece077c71c7e282f071f830747b2abb5718018cbfa699.gif",
      "analytics_identifier": "HackSimBuild 2024 - Registration is Open! (18731)",
      "url": "https://hacksimbuild-2024.devpost.com/",
      "time_left_to_submission": "Upcoming",
      "submission_period_dates": "May 19 - 20, 2024",
      "themes": [
        {
          "id": 18,
          "name": "Design"
        },
        {
          "id": 2,
          "name": "DevOps"
        },
        {
          "id": 13,
          "name": "Social Good"
        }
      ],
      "prize_amount": "$<span data-currency-value>1,000</span>",
      "registrations_count": 29,
      "featured": false,
      "organization_name": "IBPSA-USA",
      "winners_announced": false,
      "submission_gallery_url": "https://hacksimbuild-2024.devpost.com/project-gallery",
      "start_a_submission_url": "https://hacksimbuild-2024.devpost.com/challenges/start_a_submission",
      "invite_only": false,
      "eligibility_requirement_invite_only_description": null,
      "managed_by_devpost_badge": false
    },
    {
      "id": 19305,
      "title": "Hack The Skies",
      "displayed_location": {
        "icon": "map-marker-alt",
        "location": "Toronto"
      },
      "open_state": "upcoming",
      "thumbnail_url": "//d112y698adiu2z.cloudfront.net/photos/production/challenge_thumbnails/002/709/441/datas/medium_square.png",
      "analytics_identifier": "Hack The Skies (19305)",
      "url": "https://hack-the-skies.devpost.com/",
      "time_left_to_submission": "Upcoming",
      "submission_period_dates": "May 18 - 19, 2024",
      "themes": [
        {
          "id": 18,
          "name": "Design"
        },
        {
          "id": 19,
          "name": "Education"
        },
        {
          "id": 23,
          "name": "Beginner Friendly"
        }
      ],
      "prize_amount": "$<span data-currency-value>0</span>",
      "registrations_count": 24,
      "featured": false,
      "organization_name": "Hack The Skies",
      "winners_announced": false,
      "submission_gallery_url": "https://hack-the-skies.devpost.com/project-gallery",
      "start_a_submission_url": "https://hack-the-skies.devpost.com/challenges/start_a_submission",
      "invite_only": false,
      "eligibility_requirement_invite_only_description": null,
      "managed_by_devpost_badge": false
    },
    {
      "id": 21355,
      "title": "Workflo Hacks 2024",
      "displayed_location": {
        "icon": "map-marker-alt",
        "location": "Toronto Metropolitan University"
      },
      "open_state": "upcoming",
      "thumbnail_url": "//d112y698adiu2z.cloudfront.net/photos/production/challenge_thumbnails/002/873/638/datas/medium_square.png",
      "analytics_identifier": "Workflo Hacks 2024 (21355)",
      "url": "https://workflo.devpost.com/",
      "time_left_to_submission": "Upcoming",
      "submission_period_dates": "Jun 01 - 02, 2024",
      "themes": [
        {
          "id": 21,
          "name": "Enterprise"
        },
        {
          "id": 12,
          "name": "Lifehacks"
        },
        {
          "id": 11,
          "name": "Productivity"
        }
      ],
      "prize_amount": "$CAD<span data-currency-value>1,000</span>",
      "registrations_count": 18,
      "featured": false,
      "organization_name": "workflo",
      "winners_announced": false,
      "submission_gallery_url": "https://workflo.devpost.com/project-gallery",
      "start_a_submission_url": "https://workflo.devpost.com/challenges/start_a_submission",
      "invite_only": false,
      "eligibility_requirement_invite_only_description": null,
      "managed_by_devpost_badge": false
    },
    {
      "id": 21224,
      "title": "Interledger Hackathon 2024",
      "displayed_location": {
        "icon": "map-marker-alt",
        "location": "University of Cape Town"
      },
      "open_state": "upcoming",
      "thumbnail_url": "https://d2dmyh35ffsxbl.cloudfront.net/assets/defaults/thumbnail-placeholder-8c916ef4da99a222ce6ece077c71c7e282f071f830747b2abb5718018cbfa699.gif",
      "analytics_identifier": "Interledger Hackathon 2024 (21224)",
      "url": "https://interledger-hackathon-2024.devpost.com/",
      "time_left_to_submission": "Upcoming",
      "submission_period_dates": "Oct 19 - 20, 2024",
      "themes": [
        {
          "id": 23,
          "name": "Beginner Friendly"
        },
        {
          "id": 3,
          "name": "Fintech"
        },
        {
          "id": 25,
          "name": "Web"
        }
      ],
      "prize_amount": "$<span data-currency-value>9,000</span>",
      "registrations_count": 17,
      "featured": false,
      "organization_name": "Interledger Foundation",
      "winners_announced": false,
      "submission_gallery_url": "https://interledger-hackathon-2024.devpost.com/project-gallery",
      "start_a_submission_url": "https://interledger-hackathon-2024.devpost.com/challenges/start_a_submission",
      "invite_only": false,
      "eligibility_requirement_invite_only_description": null,
      "managed_by_devpost_badge": false
    },
    {
      "id": 21183,
      "title": "ETH Cape Town 2024",
      "displayed_location": {
        "icon": "map-marker-alt",
        "location": "The Watershed (Waterfront)"
      },
      "open_state": "upcoming",
      "thumbnail_url": "//d112y698adiu2z.cloudfront.net/photos/production/challenge_thumbnails/002/842/773/datas/medium_square.png",
      "analytics_identifier": "ETH Cape Town 2024 (21183)",
      "url": "https://eth-cape-town-2024.devpost.com/",
      "time_left_to_submission": "Upcoming",
      "submission_period_dates": "Sep 20 - 22, 2024",
      "themes": [
        {
          "id": 23,
          "name": "Beginner Friendly"
        },
        {
          "id": 1,
          "name": "Blockchain"
        },
        {
          "id": 4,
          "name": "Gaming"
        }
      ],
      "prize_amount": "$<span data-currency-value>6,000</span>",
      "registrations_count": 14,
      "featured": false,
      "organization_name": "ETHCapeTown",
      "winners_announced": false,
      "submission_gallery_url": "https://eth-cape-town-2024.devpost.com/project-gallery",
      "start_a_submission_url": "https://eth-cape-town-2024.devpost.com/challenges/start_a_submission",
      "invite_only": false,
      "eligibility_requirement_invite_only_description": null,
      "managed_by_devpost_badge": false
    },
    {
      "id": 20727,
      "title": "hackMHS IX",
      "displayed_location": {
        "icon": "map-marker-alt",
        "location": "Millburn High School"
      },
      "open_state": "upcoming",
      "thumbnail_url": "//d112y698adiu2z.cloudfront.net/photos/production/challenge_thumbnails/002/789/575/datas/medium_square.png",
      "analytics_identifier": "hackMHS IX (20727)",
      "url": "https://hackmhs-ix.devpost.com/",
      "time_left_to_submission": "Upcoming",
      "submission_period_dates": "May 17 - 18, 2024",
      "themes": [
        {
          "id": 23,
          "name": "Beginner Friendly"
        },
        {
          "id": 19,
          "name": "Education"
        },
        {
          "id": 13,
          "name": "Social Good"
        }
      ],
      "prize_amount": "$<span data-currency-value>13,712</span>",
      "registrations_count": 13,
      "featured": false,
      "organization_name": "HackMHS",
      "winners_announced": false,
      "submission_gallery_url": "https://hackmhs-ix.devpost.com/project-gallery",
      "start_a_submission_url": "https://hackmhs-ix.devpost.com/challenges/start_a_submission",
      "invite_only": false,
      "eligibility_requirement_invite_only_description": null,
      "managed_by_devpost_badge": false
    },
    {
      "id": 20368,
      "title": "Hoya Hacks 2025",
      "displayed_location": {
        "icon": "map-marker-alt",
        "location": "Healey Family Student Center"
      },
      "open_state": "upcoming",
      "thumbnail_url": "//d112y698adiu2z.cloudfront.net/photos/production/challenge_thumbnails/002/809/856/datas/medium_square.png",
      "analytics_identifier": "Hoya Hacks 2025 (20368)",
      "url": "https://hoya-hacks-2025.devpost.com/",
      "time_left_to_submission": "Upcoming",
      "submission_period_dates": "Jan 24 - 26, 2025",
      "themes": [
        {
          "id": 23,
          "name": "Beginner Friendly"
        },
        {
          "id": 13,
          "name": "Social Good"
        }
      ],
      "prize_amount": "$<span data-currency-value>1,500</span>",
      "registrations_count": 9,
      "featured": false,
      "organization_name": "Hoya Hacks",
      "winners_announced": false,
      "submission_gallery_url": "https://hoya-hacks-2025.devpost.com/project-gallery",
      "start_a_submission_url": "https://hoya-hacks-2025.devpost.com/challenges/start_a_submission",
      "invite_only": false,
      "eligibility_requirement_invite_only_description": null,
      "managed_by_devpost_badge": false
    },
    {
      "id": 21289,
      "title": "HSN Hacks",
      "displayed_location": {
        "icon": "map-marker-alt",
        "location": "WWP High School North"
      },
      "open_state": "upcoming",
      "thumbnail_url": "//d112y698adiu2z.cloudfront.net/photos/production/challenge_thumbnails/002/879/159/datas/medium_square.png",
      "analytics_identifier": "HSN Hacks (21289)",
      "url": "https://hsn-hacks-21289.devpost.com/",
      "time_left_to_submission": "Upcoming",
      "submission_period_dates": "May 25, 2024",
      "themes": [
        {
          "id": 23,
          "name": "Beginner Friendly"
        },
        {
          "id": 13,
          "name": "Social Good"
        },
        {
          "id": 25,
          "name": "Web"
        }
      ],
      "prize_amount": "$<span data-currency-value>1,000</span>",
      "registrations_count": 7,
      "featured": false,
      "organization_name": "WWP",
      "winners_announced": false,
      "submission_gallery_url": "https://hsn-hacks-21289.devpost.com/project-gallery",
      "start_a_submission_url": "https://hsn-hacks-21289.devpost.com/challenges/start_a_submission",
      "invite_only": false,
      "eligibility_requirement_invite_only_description": null,
      "managed_by_devpost_badge": false
    },
    {
      "id": 20686,
      "title": "HackPrix",
      "displayed_location": {
        "icon": "map-marker-alt",
        "location": "Lords Institute"
      },
      "open_state": "upcoming",
      "thumbnail_url": "//d112y698adiu2z.cloudfront.net/photos/production/challenge_thumbnails/002/845/569/datas/medium_square.png",
      "analytics_identifier": "HackPrix (20686)",
      "url": "https://hackprix.devpost.com/",
      "time_left_to_submission": "Upcoming",
      "submission_period_dates": "Jun 08 - 09, 2024",
      "themes": [
        {
          "id": 1,
          "name": "Blockchain"
        },
        {
          "id": 6,
          "name": "Machine Learning/AI"
        },
        {
          "id": 22,
          "name": "Open Ended"
        }
      ],
      "prize_amount": "₹ <span data-currency-value>0</span>",
      "registrations_count": 6,
      "featured": false,
      "organization_name": "CodeWave Hub",
      "winners_announced": false,
      "submission_gallery_url": "https://hackprix.devpost.com/project-gallery",
      "start_a_submission_url": "https://hackprix.devpost.com/challenges/start_a_submission",
      "invite_only": false,
      "eligibility_requirement_invite_only_description": null,
      "managed_by_devpost_badge": false
    },
    {
      "id": 20417,
      "title": "Ssssss",
      "displayed_location": {
        "icon": "map-marker-alt",
        "location": "Paralelní Polis"
      },
      "open_state": "upcoming",
      "thumbnail_url": "https://d2dmyh35ffsxbl.cloudfront.net/assets/defaults/thumbnail-placeholder-8c916ef4da99a222ce6ece077c71c7e282f071f830747b2abb5718018cbfa699.gif",
      "analytics_identifier": "Ssssss (20417)",
      "url": "https://monerokon.devpost.com/",
      "time_left_to_submission": "Upcoming",
      "submission_period_dates": "Jun 07 - 09, 2024",
      "themes": [
        {
          "id": 1,
          "name": "Blockchain"
        },
        {
          "id": 9,
          "name": "Cybersecurity"
        }
      ],
      "prize_amount": "€<span data-currency-value>1</span>",
      "registrations_count": 6,
      "featured": false,
      "organization_name": "MoneroKon",
      "winners_announced": false,
      "submission_gallery_url": "https://monerokon.devpost.com/project-gallery",
      "start_a_submission_url": "https://monerokon.devpost.com/challenges/start_a_submission",
      "invite_only": false,
      "eligibility_requirement_invite_only_description": null,
      "managed_by_devpost_badge": false
    },
    {
      "id": 21285,
      "title": "SafeHacks",
      "displayed_location": {
        "icon": "map-marker-alt",
        "location": "VISST"
      },
      "open_state": "upcoming",
      "thumbnail_url": "//d112y698adiu2z.cloudfront.net/photos/production/challenge_thumbnails/002/859/779/datas/medium_square.png",
      "analytics_identifier": "SafeHacks (21285)",
      "url": "https://safehacks.devpost.com/",
      "time_left_to_submission": "Upcoming",
      "submission_period_dates": "Jun 08 - 09, 2024",
      "themes": [
        {
          "id": 23,
          "name": "Beginner Friendly"
        },
        {
          "id": 9,
          "name": "Cybersecurity"
        }
      ],
      "prize_amount": "$CAD<span data-currency-value>9,571</span>",
      "registrations_count": 6,
      "featured": false,
      "organization_name": "XdHacks Mini",
      "winners_announced": false,
      "submission_gallery_url": "https://safehacks.devpost.com/project-gallery",
      "start_a_submission_url": "https://safehacks.devpost.com/challenges/start_a_submission",
      "invite_only": false,
      "eligibility_requirement_invite_only_description": null,
      "managed_by_devpost_badge": false
    },
    {
      "id": 21170,
      "title": "FidHacks 2024",
      "displayed_location": {
        "icon": "map-marker-alt",
        "location": "Fidelity Investments"
      },
      "open_state": "upcoming",
      "thumbnail_url": "//d112y698adiu2z.cloudfront.net/photos/production/challenge_thumbnails/002/851/766/datas/medium_square.png",
      "analytics_identifier": "FidHacks 2024 (21170)",
      "url": "https://fidhacks-2024.devpost.com/",
      "time_left_to_submission": "Upcoming",
      "submission_period_dates": "May 16 - 17, 2024",
      "themes": [
        {
          "id": 3,
          "name": "Fintech"
        },
        {
          "id": 13,
          "name": "Social Good"
        },
        {
          "id": 25,
          "name": "Web"
        }
      ],
      "prize_amount": "$<span data-currency-value>500</span>",
      "registrations_count": 5,
      "featured": false,
      "organization_name": "Fidelity Investments",
      "winners_announced": false,
      "submission_gallery_url": "https://fidhacks-2024.devpost.com/project-gallery",
      "start_a_submission_url": "https://fidhacks-2024.devpost.com/challenges/start_a_submission",
      "invite_only": true,
      "eligibility_requirement_invite_only_description": "Students who applied and were accepted to FidHacks",
      "managed_by_devpost_badge": false
    },
    {
      "id": 21203,
      "title": "BC HACKS 2024",
      "displayed_location": {
        "icon": "map-marker-alt",
        "location": "Bellevue College"
      },
      "open_state": "upcoming",
      "thumbnail_url": "//d112y698adiu2z.cloudfront.net/photos/production/challenge_thumbnails/002/887/631/datas/medium_square.png",
      "analytics_identifier": "BC HACKS 2024 (21203)",
      "url": "https://bc-hacks-2024.devpost.com/",
      "time_left_to_submission": "Upcoming",
      "submission_period_dates": "Jun 08 - 09, 2024",
      "themes": [
        {
          "id": 23,
          "name": "Beginner Friendly"
        },
        {
          "id": 6,
          "name": "Machine Learning/AI"
        },
        {
          "id": 25,
          "name": "Web"
        }
      ],
      "prize_amount": "$<span data-currency-value>600</span>",
      "registrations_count": 5,
      "featured": false,
      "organization_name": "BC Tech Society ",
      "winners_announced": false,
      "submission_gallery_url": "https://bc-hacks-2024.devpost.com/project-gallery",
      "start_a_submission_url": "https://bc-hacks-2024.devpost.com/challenges/start_a_submission",
      "invite_only": false,
      "eligibility_requirement_invite_only_description": null,
      "managed_by_devpost_badge": false
    },
    {
      "id": 21241,
      "title": "MY-HACK",
      "displayed_location": {
        "icon": "map-marker-alt",
        "location": "Adams Islamic Center"
      },
      "open_state": "upcoming",
      "thumbnail_url": "//d112y698adiu2z.cloudfront.net/photos/production/challenge_thumbnails/002/850/528/datas/medium_square.png",
      "analytics_identifier": "MY-HACK (21241)",
      "url": "https://my-hack-24.devpost.com/",
      "time_left_to_submission": "Upcoming",
      "submission_period_dates": "Jul 13 - 14, 2024",
      "themes": [
        {
          "id": 23,
          "name": "Beginner Friendly"
        },
        {
          "id": 6,
          "name": "Machine Learning/AI"
        },
        {
          "id": 13,
          "name": "Social Good"
        }
      ],
      "prize_amount": "$<span data-currency-value>500</span>",
      "registrations_count": 5,
      "featured": false,
      "organization_name": "Mafiq Foundation",
      "winners_announced": false,
      "submission_gallery_url": "https://my-hack-24.devpost.com/project-gallery",
      "start_a_submission_url": "https://my-hack-24.devpost.com/challenges/start_a_submission",
      "invite_only": false,
      "eligibility_requirement_invite_only_description": null,
      "managed_by_devpost_badge": false
    },
    {
      "id": 21383,
      "title": "TritonHacks 2024",
      "displayed_location": {
        "icon": "map-marker-alt",
        "location": "UC San Diego - CSE Building EBU3"
      },
      "open_state": "upcoming",
      "thumbnail_url": "//d112y698adiu2z.cloudfront.net/photos/production/challenge_thumbnails/002/879/292/datas/medium_square.png",
      "analytics_identifier": "TritonHacks 2024 (21383)",
      "url": "https://tritonhacks-2024.devpost.com/",
      "time_left_to_submission": "Upcoming",
      "submission_period_dates": "May 19, 2024",
      "themes": [
        {
          "id": 23,
          "name": "Beginner Friendly"
        },
        {
          "id": 19,
          "name": "Education"
        },
        {
          "id": 13,
          "name": "Social Good"
        }
      ],
      "prize_amount": "$<span data-currency-value>1,679</span>",
      "registrations_count": 4,
      "featured": false,
      "organization_name": "CS foreach",
      "winners_announced": false,
      "submission_gallery_url": "https://tritonhacks-2024.devpost.com/project-gallery",
      "start_a_submission_url": "https://tritonhacks-2024.devpost.com/challenges/start_a_submission",
      "invite_only": true,
      "eligibility_requirement_invite_only_description": "High School Students in the US",
      "managed_by_devpost_badge": false
    },
    {
      "id": 21246,
      "title": "Milpitas Hacks",
      "displayed_location": {
        "icon": "map-marker-alt",
        "location": "Milpitas High School Theater"
      },
      "open_state": "upcoming",
      "thumbnail_url": "//d112y698adiu2z.cloudfront.net/photos/production/challenge_thumbnails/002/850/639/datas/medium_square.png",
      "analytics_identifier": "Milpitas Hacks (21246)",
      "url": "https://milpitas-hacks.devpost.com/",
      "time_left_to_submission": "Upcoming",
      "submission_period_dates": "May 25, 2024",
      "themes": [
        {
          "id": 23,
          "name": "Beginner Friendly"
        },
        {
          "id": 3,
          "name": "Fintech"
        },
        {
          "id": 6,
          "name": "Machine Learning/AI"
        }
      ],
      "prize_amount": "$<span data-currency-value>1,610</span>",
      "registrations_count": 3,
      "featured": false,
      "organization_name": "Milpitas Hacks",
      "winners_announced": false,
      "submission_gallery_url": "https://milpitas-hacks.devpost.com/project-gallery",
      "start_a_submission_url": "https://milpitas-hacks.devpost.com/challenges/start_a_submission",
      "invite_only": false,
      "eligibility_requirement_invite_only_description": null,
      "managed_by_devpost_badge": false
    },
    {
      "id": 20533,
      "title": "LinceHacks",
      "displayed_location": {
        "icon": "map-marker-alt",
        "location": "Universidad del Norte, Monterrey"
      },
      "open_state": "upcoming",
      "thumbnail_url": "//d112y698adiu2z.cloudfront.net/photos/production/challenge_thumbnails/002/758/854/datas/medium_square.jpg",
      "analytics_identifier": "LinceHacks (20533)",
      "url": "https://lincehacks.devpost.com/",
      "time_left_to_submission": "Upcoming",
      "submission_period_dates": "May 25 - 26, 2024",
      "themes": [
        {
          "id": 12,
          "name": "Lifehacks"
        },
        {
          "id": 11,
          "name": "Productivity"
        },
        {
          "id": 13,
          "name": "Social Good"
        }
      ],
      "prize_amount": "MEX$<span data-currency-value>0</span>",
      "registrations_count": 2,
      "featured": false,
      "organization_name": "Cubit",
      "winners_announced": false,
      "submission_gallery_url": "https://lincehacks.devpost.com/project-gallery",
      "start_a_submission_url": "https://lincehacks.devpost.com/challenges/start_a_submission",
      "invite_only": false,
      "eligibility_requirement_invite_only_description": null,
      "managed_by_devpost_badge": false
    },
    {
      "id": 21405,
      "title": "Latina Blockchain Hackathon",
      "displayed_location": {
        "icon": "map-marker-alt",
        "location": "Universidad de Lima, Lima - Perú"
      },
      "open_state": "upcoming",
      "thumbnail_url": "//d112y698adiu2z.cloudfront.net/photos/production/challenge_thumbnails/002/883/321/datas/medium_square.jpg",
      "analytics_identifier": "Latina Blockchain Hackathon (21405)",
      "url": "https://latina-blockchain-hackathon.devpost.com/",
      "time_left_to_submission": "Upcoming",
      "submission_period_dates": "May 13 - 17, 2024",
      "themes": [
        {
          "id": 1,
          "name": "Blockchain"
        }
      ],
      "prize_amount": "$<span data-currency-value>16,000</span>",
      "registrations_count": 1,
      "featured": false,
      "organization_name": "Women Biz",
      "winners_announced": false,
      "submission_gallery_url": "https://latina-blockchain-hackathon.devpost.com/project-gallery",
      "start_a_submission_url": "https://latina-blockchain-hackathon.devpost.com/challenges/start_a_submission",
      "invite_only": false,
      "eligibility_requirement_invite_only_description": null,
      "managed_by_devpost_badge": false
    },
    {
      "id": 21431,
      "title": "AcademiesHacks 2024",
      "displayed_location": {
        "icon": "map-marker-alt",
        "location": "Academies of Loudoun"
      },
      "open_state": "upcoming",
      "thumbnail_url": "//d112y698adiu2z.cloudfront.net/photos/production/challenge_thumbnails/002/886/536/datas/medium_square.png",
      "analytics_identifier": "AcademiesHacks 2024 (21431)",
      "url": "https://aclhacks24.devpost.com/",
      "time_left_to_submission": "Upcoming",
      "submission_period_dates": "May 18 - 19, 2024",
      "themes": [
        {
          "id": 23,
          "name": "Beginner Friendly"
        },
        {
          "id": 19,
          "name": "Education"
        }
      ],
      "prize_amount": "$<span data-currency-value>2,052</span>",
      "registrations_count": 1,
      "featured": false,
      "organization_name": "Academies of Loudoun",
      "winners_announced": false,
      "submission_gallery_url": "https://aclhacks24.devpost.com/project-gallery",
      "start_a_submission_url": "https://aclhacks24.devpost.com/challenges/start_a_submission",
      "invite_only": true,
      "eligibility_requirement_invite_only_description": "Students attending ACL hacks. ",
      "managed_by_devpost_badge": false
    },
    {
      "id": 21378,
      "title": "Neodata Hackathon Catania",
      "displayed_location": {
        "icon": "map-marker-alt",
        "location": "Isola - Catania"
      },
      "open_state": "upcoming",
      "thumbnail_url": "//d112y698adiu2z.cloudfront.net/photos/production/challenge_thumbnails/002/886/276/datas/medium_square.png",
      "analytics_identifier": "Neodata Hackathon Catania (21378)",
      "url": "https://neodata-hackatania.devpost.com/",
      "time_left_to_submission": "Upcoming",
      "submission_period_dates": "May 24 - 27, 2024",
      "themes": [
        {
          "id": 23,
          "name": "Beginner Friendly"
        },
        {
          "id": 21,
          "name": "Enterprise"
        },
        {
          "id": 6,
          "name": "Machine Learning/AI"
        }
      ],
      "prize_amount": "€<span data-currency-value>750</span>",
      "registrations_count": 1,
      "featured": false,
      "organization_name": "Neodata",
      "winners_announced": false,
      "submission_gallery_url": "https://neodata-hackatania.devpost.com/project-gallery",
      "start_a_submission_url": "https://neodata-hackatania.devpost.com/challenges/start_a_submission",
      "invite_only": false,
      "eligibility_requirement_invite_only_description": null,
      "managed_by_devpost_badge": false
    },
    {
      "id": 21299,
      "title": "CodeDay New York",
      "displayed_location": {
        "icon": "map-marker-alt",
        "location": "Flatiron School in Manhattan, NY"
      },
      "open_state": "upcoming",
      "thumbnail_url": "//d112y698adiu2z.cloudfront.net/photos/production/challenge_thumbnails/002/876/619/datas/medium_square.png",
      "analytics_identifier": "CodeDay New York (21299)",
      "url": "https://codeday-new-york.devpost.com/",
      "time_left_to_submission": "Upcoming",
      "submission_period_dates": "Jun 29, 2024",
      "themes": [
        {
          "id": 23,
          "name": "Beginner Friendly"
        },
        {
          "id": 15,
          "name": "Music/Art"
        },
        {
          "id": 22,
          "name": "Open Ended"
        }
      ],
      "prize_amount": "$<span data-currency-value>0</span>",
      "registrations_count": 1,
      "featured": false,
      "organization_name": "CodeDay",
      "winners_announced": false,
      "submission_gallery_url": "https://codeday-new-york.devpost.com/project-gallery",
      "start_a_submission_url": "https://codeday-new-york.devpost.com/challenges/start_a_submission",
      "invite_only": false,
      "eligibility_requirement_invite_only_description": null,
      "managed_by_devpost_badge": false
    }
  ],
  "meta": {
    "total_count": 34,
    "per_page": 40,
    "fuzzy": false
  }
}
